recyclebin/__init__.py
recyclebin/apps.py
recyclebin/functions.py
recyclebin/models.py
recyclebin/serializers.py
recyclebin/utils.py
recyclebin/migrations/__init__.py
django_recyclebin-0.1.dist-info/LICENSE
django_recyclebin-0.1.dist-info/METADATA
django_recyclebin-0.1.dist-info/WHEEL
django_recyclebin-0.1.dist-info/top_level.txt
django_recyclebin-0.1.dist-info/RECORD
