Metadata-Version: 2.1
Name: django-recyclebin
Version: 0.1
Summary: A Django app to make recyclebin.
Home-page: https://github.com/abraffay/django-recyclebin
Author: Abdul Raffay
Author-email: abdulraffahmehtab@gmail.com
License: UNKNOWN
Project-URL: Bug Tracker, https://github.com/abraffay/django-recyclebin/issues
Platform: UNKNOWN
Classifier: Environment :: Web Environment
Classifier: Framework :: Django
Classifier: Framework :: Django :: 2.2
Classifier: Intended Audience :: Developers
Classifier: Operating System :: OS Independent
Classifier: Programming Language :: Python :: 3
Classifier: License :: OSI Approved :: MIT License
Classifier: Topic :: Internet :: WWW/HTTP
Classifier: Topic :: Internet :: WWW/HTTP :: Dynamic Content
Requires-Python: >=3.6
License-File: LICENSE
Requires-Dist: Django (>=2.2)
Requires-Dist: djangorestframework (>=3.2)
